interscity_client/__init__.py
interscity_client/exceptions.py
interscity_client/platform.py
interscity_client-0.2.1.dist-info/COPYING
interscity_client-0.2.1.dist-info/METADATA
interscity_client-0.2.1.dist-info/WHEEL
interscity_client-0.2.1.dist-info/top_level.txt
interscity_client-0.2.1.dist-info/RECORD
