Metadata-Version: 2.1
Name: interscity-client
Version: 0.2.1
Summary: InterSCity client
Home-page: http://github.com/DylanGuedes/interscity_client
Author: Dylan Guedes
Author-email: djmgguedes@gmail.com
License: MIT
Platform: UNKNOWN
